trie_again/__init__.py
trie_again/trie.py
trie_again-0.1.0.dist-info/METADATA
trie_again-0.1.0.dist-info/WHEEL
trie_again-0.1.0.dist-info/LICENSE
trie_again-0.1.0.dist-info/RECORD
